icondetection/__init__.py
icondetection/box.py
icondetection/helpers.py
icondetection/manual_test.py
icondetection/rectangle.py
icondetection/weighted_quick_unionUF.py
icondetection/demo/__init__.py
icondetection/demo/demo.py
icondetection-0.1.0.dist-info/LICENSE.txt
icondetection-0.1.0.dist-info/METADATA
icondetection-0.1.0.dist-info/WHEEL
icondetection-0.1.0.dist-info/top_level.txt
icondetection-0.1.0.dist-info/RECORD
