Metadata-Version: 2.1
Name: icondetection
Version: 0.1.0
Summary: Detect icons on the screen easily and quickly.
Home-page: https://github.com/luiszugasti/IconMatch
Author: Luis Zugasti
Author-email: hello@luiszugasti.me
License: MIT
Platform: UNKNOWN
Classifier: License :: OSI Approved :: MIT License
Classifier: Programming Language :: Python :: 3.8
Requires-Python: >=3.8
Requires-Dist: Pillow
Requires-Dist: opencv-contrib-python
Requires-Dist: numpy
